boxnotes2html/__init__.py
boxnotes2html/boxnote.py
boxnotes2html/cli.py
boxnotes2html/html.py
boxnotes2html/markdown.py
boxnotes2html/style.css
boxnotes2html/table.py
boxnotes2html-0.1.4.dist-info/LICENSE
boxnotes2html-0.1.4.dist-info/METADATA
boxnotes2html-0.1.4.dist-info/WHEEL
boxnotes2html-0.1.4.dist-info/entry_points.txt
boxnotes2html-0.1.4.dist-info/top_level.txt
boxnotes2html-0.1.4.dist-info/RECORD
