Metadata-Version: 2.1
Name: boxnotes2html
Version: 0.1.4
Summary: Converting from Box Notes to HTML or other formats
Home-page: https://github.com/alexwennerberg/boxnotes2html
Author: Alex Wennerberg
Author-email: alex@alexwennerberg.com
License: UNKNOWN
Platform: UNKNOWN
Classifier: Development Status :: 3 - Alpha
Classifier: Programming Language :: Python :: 3
